MANIFEST.in
README.md
setup.py
test_banchan.py
banchan/__init__.py
banchan/cache.py
banchan/crypt.py
banchan/csv_.py
banchan/date.py
banchan/ds.py
banchan/emit.py
banchan/format.py
banchan/geo.py
banchan/hash.py
banchan/html.py
banchan/image.py
banchan/json_.py
banchan/log.py
banchan/math_.py
banchan/meta.py
banchan/module.py
banchan/name.py
banchan/net.py
banchan/parse.py
banchan/pickle.py
banchan/profiler.py
banchan/random_.py
banchan/robust.py
banchan/route.py
banchan/system.py
banchan/text.py
banchan/timeout.py
banchan/url.py
banchan.egg-info/PKG-INFO
banchan.egg-info/SOURCES.txt
banchan.egg-info/dependency_links.txt
banchan.egg-info/not-zip-safe
banchan.egg-info/top_level.txt