Metadata-Version: 1.0
Name: banchan
Version: 0.0.3
Summary: Collection of small Python utilities
Home-page: https://github.com/mjipeo/banchan
Author: Minjong Chung
Author-email: mjipeo@gmail.com
License: Apache 2.0
Platform: UNKNOWN
